reduced_3dgs/__init__.py
reduced_3dgs/combinations.py
reduced_3dgs/prepare.py
reduced_3dgs/quantize.py
reduced_3dgs/train.py
reduced_3dgs/diff_gaussian_rasterization/_C.cp311-win_amd64.pyd
reduced_3dgs/diff_gaussian_rasterization/__init__.py
reduced_3dgs/importance/__init__.py
reduced_3dgs/importance/combinations.py
reduced_3dgs/importance/trainer.py
reduced_3dgs/importance/diff_gaussian_rasterization/_C.cp311-win_amd64.pyd
reduced_3dgs/importance/diff_gaussian_rasterization/__init__.py
reduced_3dgs/pruning/__init__.py
reduced_3dgs/pruning/combinations.py
reduced_3dgs/pruning/trainer.py
reduced_3dgs/quantization/__init__.py
reduced_3dgs/quantization/abc.py
reduced_3dgs/quantization/exclude_zeros.py
reduced_3dgs/quantization/quantizer.py
reduced_3dgs/quantization/wrapper.py
reduced_3dgs/shculling/__init__.py
reduced_3dgs/shculling/gaussian_model.py
reduced_3dgs/shculling/trainer.py
reduced_3dgs/simple_knn/_C.cp311-win_amd64.pyd
reduced_3dgs-1.12.8.dist-info/licenses/LICENSE.md
reduced_3dgs-1.12.8.dist-info/METADATA
reduced_3dgs-1.12.8.dist-info/WHEEL
reduced_3dgs-1.12.8.dist-info/top_level.txt
reduced_3dgs-1.12.8.dist-info/RECORD
