Metadata-Version: 2.4
Name: reduced_3dgs
Version: 1.12.8
Summary: Refactored code for the paper "Reducing the Memory Footprint of 3D Gaussian Splatting"
Home-page: https://github.com/yindaheng98/reduced-3dgs
Author: yindaheng98
Author-email: yindaheng98@gmail.com
Classifier: Programming Language :: Python :: 3
License-File: LICENSE.md
Requires-Dist: gaussian-splatting
Requires-Dist: scikit-learn
Dynamic: author
Dynamic: author-email
Dynamic: classifier
Dynamic: description
Dynamic: description-content-type
Dynamic: home-page
Dynamic: license-file
Dynamic: requires-dist
Dynamic: summary
